model_pack/Features.py
model_pack/Load_Data.py
model_pack/Pipeline.py
model_pack/Train_Model.py
model_pack/Train_Test_split.py
model_pack/Train_Val_Predict.py
model_pack/VERSION
model_pack/__init__.py
model_pack/Config/__init__.py
model_pack/Config/config.yaml
model_pack/Config/config_validations.py
model_pack/Trained_models/logistic_regression_v0.0.7.pkl
titanic_twozerotwotwomar-0.0.7.dist-info/LICENSE
titanic_twozerotwotwomar-0.0.7.dist-info/METADATA
titanic_twozerotwotwomar-0.0.7.dist-info/WHEEL
titanic_twozerotwotwomar-0.0.7.dist-info/top_level.txt
titanic_twozerotwotwomar-0.0.7.dist-info/RECORD
